[
  {
    "src": "/assets/reel/reel-01.webp",
    "alt": "Werkstatt – Einblick",
    "cap": "Werkstatt – Einblick",
    "cats": [
      "custom"
    ]
  },
  {
    "src": "/assets/reel/reel-02.webp",
    "alt": "Werkstatt – Einblick",
    "cap": "Werkstatt – Einblick",
    "cats": [
      "schwibbogen"
    ]
  },
  {
    "src": "/assets/reel/reel-03.webp",
    "alt": "Werkstatt – Einblick",
    "cap": "Werkstatt – Einblick",
    "cats": [
      "holz"
    ]
  },
  {
    "src": "/assets/reel/reel-04.webp",
    "alt": "Werkstatt – Einblick",
    "cap": "Werkstatt – Einblick",
    "cats": [
      "schiefer"
    ]
  },
  {
    "src": "/assets/reel/reel-05.webp",
    "alt": "Werkstatt – Einblick",
    "cap": "Werkstatt – Einblick",
    "cats": [
      "schwibbogen"
    ]
  },
  {
    "src": "/assets/reel/reel-06.webp",
    "alt": "Werkstatt – Einblick",
    "cap": "Werkstatt – Einblick",
    "cats": [
      "metall"
    ]
  },
  {
    "src": "/assets/reel/reel-07.webp",
    "alt": "Werkstatt – Einblick",
    "cap": "Werkstatt – Einblick",
    "cats": [
      "metall"
    ]
  },
  {
    "src": "/assets/reel/reel-08.webp",
    "alt": "Werkstatt – Einblick",
    "cap": "Werkstatt – Einblick",
    "cats": [
      "holz"
    ]
  },
  {
    "src": "/assets/reel/reel-09.webp",
    "alt": "Werkstatt – Einblick",
    "cap": "Werkstatt – Einblick",
    "cats": [
      "acryl"
    ]
  },
  {
    "src": "/assets/reel/reel-10.webp",
    "alt": "Werkstatt – Einblick",
    "cap": "Werkstatt – Einblick",
    "cats": [
      "custom"
    ]
  },
  {
    "src": "/assets/reel/reel-11.webp",
    "alt": "Werkstatt – Einblick",
    "cap": "Werkstatt – Einblick",
    "cats": [
      "metall"
    ]
  },
  {
    "src": "/assets/reel/reel-12.webp",
    "alt": "Werkstatt – Einblick",
    "cap": "Werkstatt – Einblick",
    "cats": [
      "custom"
    ]
  },
  {
    "src": "/assets/reel/reel-13.webp",
    "alt": "Werkstatt – Einblick",
    "cap": "Werkstatt – Einblick",
    "cats": [
      "schwibbogen"
    ]
  },
  {
    "src": "/assets/reel/reel-14.webp",
    "alt": "Werkstatt – Einblick",
    "cap": "Werkstatt – Einblick",
    "cats": [
      "metall"
    ]
  },
  {
    "src": "/assets/reel/reel-15.webp",
    "alt": "Werkstatt – Einblick",
    "cap": "Werkstatt – Einblick",
    "cats": [
      "custom"
    ]
  },
  {
    "src": "/assets/reel/reel-16.webp",
    "alt": "Werkstatt – Einblick",
    "cap": "Werkstatt – Einblick",
    "cats": [
      "custom"
    ]
  },
  {
    "src": "/assets/reel/reel-17.webp",
    "alt": "Werkstatt – Einblick",
    "cap": "Werkstatt – Einblick",
    "cats": [
      "schwibbogen"
    ]
  },
  {
    "src": "/assets/reel/reel-18.webp",
    "alt": "Werkstatt – Einblick",
    "cap": "Werkstatt – Einblick",
    "cats": [
      "custom"
    ]
  },
  {
    "src": "/assets/reel/reel-19.webp",
    "alt": "Werkstatt – Einblick",
    "cap": "Werkstatt – Einblick",
    "cats": [
      "schiefer"
    ]
  },
  {
    "src": "/assets/reel/reel-20.webp",
    "alt": "Werkstatt – Einblick",
    "cap": "Werkstatt – Einblick",
    "cats": [
      "glas"
    ]
  },
  {
    "src": "/assets/reel/reel-21.webp",
    "alt": "Werkstatt – Einblick",
    "cap": "Werkstatt – Einblick",
    "cats": [
      "metall"
    ]
  },
  {
    "src": "/assets/reel/reel-22.webp",
    "alt": "Werkstatt – Einblick",
    "cap": "Werkstatt – Einblick",
    "cats": [
      "custom"
    ]
  },
  {
    "src": "/assets/reel/reel-23.webp",
    "alt": "Werkstatt – Einblick",
    "cap": "Werkstatt – Einblick",
    "cats": [
      "schiefer"
    ]
  },
  {
    "src": "/assets/reel/reel-24.webp",
    "alt": "Werkstatt – Einblick",
    "cap": "Werkstatt – Einblick",
    "cats": [
      "schiefer"
    ]
  },
  {
    "src": "/assets/reel/reel-25.webp",
    "alt": "Werkstatt – Einblick",
    "cap": "Werkstatt – Einblick",
    "cats": [
      "custom"
    ]
  },
  {
    "src": "/assets/reel/reel-26.webp",
    "alt": "Werkstatt – Einblick",
    "cap": "Werkstatt – Einblick",
    "cats": [
      "glas"
    ]
  },
  {
    "src": "/assets/reel/reel-27.webp",
    "alt": "Werkstatt – Einblick",
    "cap": "Werkstatt – Einblick",
    "cats": [
      "glas"
    ]
  },
  {
    "src": "/assets/reel/reel-28.webp",
    "alt": "Werkstatt – Einblick",
    "cap": "Werkstatt – Einblick",
    "cats": [
      "glas"
    ]
  },
  {
    "src": "/assets/reel/reel-29.webp",
    "alt": "Werkstatt – Einblick",
    "cap": "Werkstatt – Einblick",
    "cats": [
      "metall"
    ]
  },
  {
    "src": "/assets/reel/reel-30.webp",
    "alt": "Werkstatt – Einblick",
    "cap": "Werkstatt – Einblick",
    "cats": [
      "custom"
    ]
  },
  {
    "src": "/assets/reel/reel-31.webp",
    "alt": "Werkstatt – Einblick",
    "cap": "Werkstatt – Einblick",
    "cats": [
      "metall"
    ]
  },
  {
    "src": "/assets/reel/reel-32.webp",
    "alt": "Werkstatt – Einblick",
    "cap": "Werkstatt – Einblick",
    "cats": [
      "custom"
    ]
  },
  {
    "src": "/assets/reel/reel-33.webp",
    "alt": "Werkstatt – Einblick",
    "cap": "Werkstatt – Einblick",
    "cats": [
      "custom"
    ]
  },
  {
    "src": "/assets/reel/reel-34.webp",
    "alt": "Werkstatt – Einblick",
    "cap": "Werkstatt – Einblick",
    "cats": [
      "glas"
    ]
  },
  {
    "src": "/assets/reel/reel-35.webp",
    "alt": "Werkstatt – Einblick",
    "cap": "Werkstatt – Einblick",
    "cats": [
      "holz"
    ]
  },
  {
    "src": "/assets/reel/reel-36.webp",
    "alt": "Werkstatt – Einblick",
    "cap": "Werkstatt – Einblick",
    "cats": [
      "custom"
    ]
  },
  {
    "src": "/assets/reel/reel-37.webp",
    "alt": "Werkstatt – Einblick",
    "cap": "Werkstatt – Einblick",
    "cats": [
      "acryl"
    ]
  },
  {
    "src": "/assets/reel/reel-38.webp",
    "alt": "Werkstatt – Einblick",
    "cap": "Werkstatt – Einblick",
    "cats": [
      "holz"
    ]
  },
  {
    "src": "/assets/reel/reel-39.webp",
    "alt": "Werkstatt – Einblick",
    "cap": "Werkstatt – Einblick",
    "cats": [
      "acryl"
    ]
  },
  {
    "src": "/assets/reel/reel-40.webp",
    "alt": "Werkstatt – Einblick",
    "cap": "Werkstatt – Einblick",
    "cats": [
      "metall"
    ]
  },
  {
    "src": "/assets/reel/reel-41.webp",
    "alt": "Werkstatt – Einblick",
    "cap": "Werkstatt – Einblick",
    "cats": [
      "metall"
    ]
  },
  {
    "src": "/assets/reel/reel-42.webp",
    "alt": "Werkstatt – Einblick",
    "cap": "Werkstatt – Einblick",
    "cats": [
      "schiefer"
    ]
  },
  {
    "src": "/assets/reel/reel-43.webp",
    "alt": "Werkstatt – Einblick",
    "cap": "Werkstatt – Einblick",
    "cats": [
      "holz"
    ]
  },
  {
    "src": "/assets/reel/reel-44.webp",
    "alt": "Werkstatt – Einblick",
    "cap": "Werkstatt – Einblick",
    "cats": [
      "metall"
    ]
  },
  {
    "src": "/assets/reel/reel-45.webp",
    "alt": "Werkstatt – Einblick",
    "cap": "Werkstatt – Einblick",
    "cats": [
      "schiefer"
    ]
  },
  {
    "src": "/assets/reel/reel-46.webp",
    "alt": "Werkstatt – Einblick",
    "cap": "Werkstatt – Einblick",
    "cats": [
      "custom"
    ]
  },
  {
    "src": "/assets/reel/reel-47.webp",
    "alt": "Werkstatt – Einblick",
    "cap": "Werkstatt – Einblick",
    "cats": [
      "metall"
    ]
  },
  {
    "src": "/assets/reel/reel-48.webp",
    "alt": "Werkstatt – Einblick",
    "cap": "Werkstatt – Einblick",
    "cats": [
      "custom"
    ]
  },
  {
    "src": "/assets/reel/reel-49.webp",
    "alt": "Werkstatt – Einblick",
    "cap": "Werkstatt – Einblick",
    "cats": [
      "metall"
    ]
  },
  {
    "src": "/assets/reel/reel-50.webp",
    "alt": "Werkstatt – Einblick",
    "cap": "Werkstatt – Einblick",
    "cats": [
      "metall"
    ]
  },
  {
    "src": "/assets/reel/reel-51.webp",
    "alt": "Werkstatt – Einblick",
    "cap": "Werkstatt – Einblick",
    "cats": [
      "custom"
    ]
  },
  {
    "src": "/assets/reel/reel-52.webp",
    "alt": "Werkstatt – Einblick",
    "cap": "Werkstatt – Einblick",
    "cats": [
      "metall"
    ]
  },
  {
    "src": "/assets/reel/reel-53.webp",
    "alt": "Werkstatt – Einblick",
    "cap": "Werkstatt – Einblick",
    "cats": [
      "metall"
    ]
  },
  {
    "src": "/assets/reel/reel-54.webp",
    "alt": "Werkstatt – Einblick",
    "cap": "Werkstatt – Einblick",
    "cats": [
      "glas"
    ]
  },
  {
    "src": "/assets/reel/reel-55.webp",
    "alt": "Werkstatt – Einblick",
    "cap": "Werkstatt – Einblick",
    "cats": [
      "holz"
    ]
  },
  {
    "src": "/assets/reel/reel-56.webp",
    "alt": "Werkstatt – Einblick",
    "cap": "Werkstatt – Einblick",
    "cats": [
      "holz"
    ]
  },
  {
    "src": "/assets/reel/reel-57.webp",
    "alt": "Werkstatt – Einblick",
    "cap": "Werkstatt – Einblick",
    "cats": [
      "metall"
    ]
  },
  {
    "src": "/assets/reel/reel-58.webp",
    "alt": "Werkstatt – Einblick",
    "cap": "Werkstatt – Einblick",
    "cats": [
      "holz"
    ]
  },
  {
    "src": "/assets/reel/reel-59.webp",
    "alt": "Werkstatt – Einblick",
    "cap": "Werkstatt – Einblick",
    "cats": [
      "schiefer"
    ]
  },
  {
    "src": "/assets/reel/reel-60.webp",
    "alt": "Werkstatt – Einblick",
    "cap": "Werkstatt – Einblick",
    "cats": [
      "holz"
    ]
  }
]
